querymate/__init__.py
querymate/py.typed
querymate/types.py
querymate/core/config.py
querymate/core/filter.py
querymate/core/grouping.py
querymate/core/query_builder.py
querymate/core/querymate.py
querymate-0.6.9.dist-info/licenses/LICENSE
querymate-0.6.9.dist-info/METADATA
querymate-0.6.9.dist-info/WHEEL
querymate-0.6.9.dist-info/top_level.txt
querymate-0.6.9.dist-info/RECORD
