Metadata-Version: 2.4
Name: querymate
Version: 0.6.9
Summary: A structured query builder for FastAPI and SQLModel
Author-email: Mauricio Banduk <mauricio@banduk.com>
License-Expression: MIT
Project-URL: Homepage, https://github.com/banduk/querymate
Project-URL: Repository, https://github.com/banduk/querymate
Requires-Python: >=3.11
License-File: LICENSE
Requires-Dist: fastapi>=0.109.0
Requires-Dist: sqlmodel>=0.0.14
Requires-Dist: pydantic>=2.6.0
Requires-Dist: pydantic-settings>=2.1.0
Requires-Dist: sqlalchemy>=2.0.0
Requires-Dist: greenlet>=3.0.0
Provides-Extra: dev
Requires-Dist: pytest>=8.0.0; extra == "dev"
Requires-Dist: pytest-cov>=4.1.0; extra == "dev"
Requires-Dist: pytest-asyncio>=0.26.0; extra == "dev"
Requires-Dist: ruff>=0.2.0; extra == "dev"
Requires-Dist: black>=24.1.0; extra == "dev"
Requires-Dist: isort>=5.13.0; extra == "dev"
Requires-Dist: mypy>=1.8.0; extra == "dev"
Requires-Dist: sphinx>=7.2.0; extra == "dev"
Requires-Dist: sphinx-rtd-theme>=2.0.0; extra == "dev"
Requires-Dist: sphinx-autodoc-typehints>=1.25.0; extra == "dev"
Requires-Dist: myst-parser>=2.0.0; extra == "dev"
Requires-Dist: sphinx-copybutton>=0.5.0; extra == "dev"
Requires-Dist: sphinx-design>=0.5.0; extra == "dev"
Requires-Dist: furo>=2024.0.0; extra == "dev"
Requires-Dist: httpx>=0.27.0; extra == "dev"
Requires-Dist: toml>=0.10.2; extra == "dev"
Requires-Dist: packaging>=24.0; extra == "dev"
Requires-Dist: build>=0.11.0; extra == "dev"
Requires-Dist: twine>=5.0.0; extra == "dev"
Requires-Dist: ipdb>=0.13.13; extra == "dev"
Requires-Dist: aiosqlite>=0.2.0; extra == "dev"
Dynamic: license-file
